indelpost-0.2.3.dist-info/METADATA
indelpost-0.2.3.dist-info/LICENSE
indelpost-0.2.3.dist-info/RECORD
indelpost-0.2.3.dist-info/top_level.txt
indelpost-0.2.3.dist-info/WHEEL
indelpost/pileup.cpython-36m-x86_64-linux-gnu.so
indelpost/consensus.py
indelpost/utilities.cpython-36m-x86_64-linux-gnu.so
indelpost/contig.cpython-36m-x86_64-linux-gnu.so
indelpost/variant.cpython-36m-x86_64-linux-gnu.so
indelpost/localn.cpython-36m-x86_64-linux-gnu.so
indelpost/__init__.py
indelpost/local_reference.cpython-36m-x86_64-linux-gnu.so
indelpost/sswpy.cpython-36m-x86_64-linux-gnu.so
indelpost/version.py
indelpost/gappedaln.cpython-36m-x86_64-linux-gnu.so
indelpost/varaln.cpython-36m-x86_64-linux-gnu.so
indelpost/softclip.cpython-36m-x86_64-linux-gnu.so
indelpost/alleles.py
