Metadata-Version: 2.1
Name: indelpost
Version: 0.2.3
Summary: Python library for simple and complex indels
Home-page: https://github.com/stjude/indelpost
Author: Kohei Hagiwara
Author-email: kohei.hagiwara@stjude.org
License: Apache License 2.0
Platform: UNKNOWN
Requires-Dist: numpy (>=1.16.0)
Requires-Dist: pysam (>=0.15.0)
Requires-Dist: cython (>=0.29.12)
